[
null,
{"id":1,"members":[{"enemyId":1,"x":177,"y":271,"hidden":false},{"enemyId":1,"x":219,"y":394,"hidden":false}],"name":"多蜜植物*2","pages":[{"conditions":{"actorHp":50,"actorId":1,"actorValid":false,"enemyHp":50,"enemyIndex":0,"enemyValid":false,"switchId":1,"switchValid":false,"turnA":0,"turnB":0,"turnEnding":false,"turnValid":false},"list":[{"code":0,"indent":0,"parameters":[]}],"span":0}]},
{"id":2,"members":[],"name":"","pages":[{"conditions":{"actorHp":50,"actorId":1,"actorValid":false,"enemyHp":50,"enemyIndex":0,"enemyValid":false,"switchId":1,"switchValid":false,"turnA":0,"turnB":0,"turnEnding":false,"turnValid":false},"list":[{"code":0,"indent":0,"parameters":[]}],"span":0}]},
{"id":3,"members":[],"name":"","pages":[{"conditions":{"actorHp":50,"actorId":1,"actorValid":false,"enemyHp":50,"enemyIndex":0,"enemyValid":false,"switchId":1,"switchValid":false,"turnA":0,"turnB":0,"turnEnding":false,"turnValid":false},"list":[{"code":0,"indent":0,"parameters":[]}],"span":0}]},
{"id":4,"members":[],"name":"","pages":[{"conditions":{"actorHp":50,"actorId":1,"actorValid":false,"enemyHp":50,"enemyIndex":0,"enemyValid":false,"switchId":1,"switchValid":false,"turnA":0,"turnB":0,"turnEnding":false,"turnValid":false},"list":[{"code":0,"indent":0,"parameters":[]}],"span":0}]},
{"id":5,"members":[],"name":"——————————","pages":[{"conditions":{"actorHp":50,"actorId":1,"actorValid":false,"enemyHp":50,"enemyIndex":0,"enemyValid":false,"switchId":1,"switchValid":false,"turnA":0,"turnB":0,"turnEnding":false,"turnValid":false},"list":[{"code":0,"indent":0,"parameters":[]}],"span":0}]},
{"id":6,"members":[{"enemyId":6,"x":192,"y":364,"hidden":false}],"name":"艾丽卡","pages":[{"conditions":{"actorHp":50,"actorId":1,"actorValid":false,"enemyHp":50,"enemyIndex":0,"enemyValid":false,"switchId":1,"switchValid":false,"turnA":0,"turnB":0,"turnEnding":false,"turnValid":false},"list":[{"code":0,"indent":0,"parameters":[]}],"span":0}]},
{"id":7,"members":[{"enemyId":8,"x":337,"y":340,"hidden":false},{"enemyId":7,"x":143,"y":241,"hidden":false},{"enemyId":7,"x":127,"y":444,"hidden":false}],"name":"圣堂大天使, 圣堂骑士*2","pages":[{"conditions":{"actorHp":50,"actorId":1,"actorValid":false,"enemyHp":50,"enemyIndex":0,"enemyValid":false,"switchId":1,"switchValid":false,"turnA":0,"turnB":0,"turnEnding":false,"turnValid":false},"list":[{"code":0,"indent":0,"parameters":[]}],"span":0}]},
{"id":8,"members":[{"enemyId":11,"x":210,"y":384,"hidden":false},{"enemyId":9,"x":222,"y":391,"hidden":false}],"name":"克里斯·裁决之龙","pages":[{"conditions":{"actorHp":50,"actorId":1,"actorValid":false,"enemyHp":50,"enemyIndex":0,"enemyValid":false,"switchId":1,"switchValid":false,"turnA":0,"turnB":0,"turnEnding":false,"turnValid":false},"list":[{"code":0,"indent":0,"parameters":[]}],"span":0}]}
]